mfft/__init__.py
mfft/basefft.py
mfft/clfft.py
mfft/cufft.py
mfft/fft.py
mfft/fftw.py
mfft/npfft.py
mfft/test/__init__.py
mfft/test/test_fft.py
mfft-0.1.1.dev0.dist-info/METADATA
mfft-0.1.1.dev0.dist-info/WHEEL
mfft-0.1.1.dev0.dist-info/top_level.txt
mfft-0.1.1.dev0.dist-info/zip-safe
mfft-0.1.1.dev0.dist-info/RECORD
