Metadata-Version: 2.1
Name: mfft
Version: 0.1.1.dev0
Summary: UNKNOWN
Home-page: UNKNOWN
Author: Pierre Paleo
Author-email: pierre.paleo@esrf.fr
Maintainer: Pierre Paleo
Maintainer-email: pierre.paleo@esrf.fr
License: UNKNOWN
Platform: UNKNOWN
Requires-Dist: numpy
